django_auth_ldap_ad/__init__.py
django_auth_ldap_ad/backend.py
django_auth_ldap_ad/models.py
django_auth_ldap_ad/tests.py
django_auth_ldap_ad-1.0.0b2.dist-info/DESCRIPTION.rst
django_auth_ldap_ad-1.0.0b2.dist-info/METADATA
django_auth_ldap_ad-1.0.0b2.dist-info/RECORD
django_auth_ldap_ad-1.0.0b2.dist-info/WHEEL
django_auth_ldap_ad-1.0.0b2.dist-info/metadata.json
django_auth_ldap_ad-1.0.0b2.dist-info/top_level.txt
