Metadata-Version: 2.0
Name: django-auth-ldap-ad
Version: 1.0.0b2
Summary: An application providing some template tags to add buttons to pages
Home-page: https://github.com/frague59/django-auth-ldap-ad
Author: Pauli
Author-email: susundberg@gmail.com
License: GPLv2
Keywords: Django,LDAP,Active Directory
Platform: UNKNOWN
Classifier: Development Status :: 4 - Beta
Classifier: Framework :: Django :: 1.9
Classifier: Framework :: Django :: 1.10
Classifier: Framework :: Django :: 1.11
Classifier: Intended Audience :: Developers
Classifier: License :: OSI Approved :: BSD License
Classifier: Operating System :: POSIX :: Linux
Classifier: Programming Language :: Python
Classifier: Topic :: System :: Systems Administration :: Authentication/Directory :: LDAP
Requires-Dist: Django (<2.0)
Requires-Dist: django-appconf
Requires-Dist: ldap
